watson/__init__.py
watson/console/__init__.py
watson/console/colors.py
watson/console/command.py
watson/console/decorators.py
watson/console/runner.py
watson/console/styles.py
watson_console-2.0.4.dist-info/AUTHORS
watson_console-2.0.4.dist-info/LICENSE
watson_console-2.0.4.dist-info/METADATA
watson_console-2.0.4.dist-info/WHEEL
watson_console-2.0.4.dist-info/top_level.txt
watson_console-2.0.4.dist-info/RECORD
